{"topicSections":[{"anchor":"Articles","generated":true,"title":"Articles","identifiers":["doc:\/\/MapsNativeSDK\/documentation\/MapsNativeSDK\/BaseConcepts","doc:\/\/MapsNativeSDK\/documentation\/MapsNativeSDK\/CameraMoving","doc:\/\/MapsNativeSDK\/documentation\/MapsNativeSDK\/Controls","doc:\/\/MapsNativeSDK\/documentation\/MapsNativeSDK\/FollowingMode","doc:\/\/MapsNativeSDK\/documentation\/MapsNativeSDK\/Gestures","doc:\/\/MapsNativeSDK\/documentation\/MapsNativeSDK\/Lifecycle","doc:\/\/MapsNativeSDK\/documentation\/MapsNativeSDK\/Markers","doc:\/\/MapsNativeSDK\/documentation\/MapsNativeSDK\/StartUsing","doc:\/\/MapsNativeSDK\/documentation\/MapsNativeSDK\/Styles","doc:\/\/MapsNativeSDK\/documentation\/MapsNativeSDK\/UpdateSdk","doc:\/\/MapsNativeSDK\/documentation\/MapsNativeSDK\/UserPointer"]},{"anchor":"Classes","generated":true,"title":"Classes","identifiers":["doc:\/\/MapsNativeSDK\/documentation\/MapsNativeSDK\/CameraController","doc:\/\/MapsNativeSDK\/documentation\/MapsNativeSDK\/MapDataSource","doc:\/\/MapsNativeSDK\/documentation\/MapsNativeSDK\/MapImageNode","doc:\/\/MapsNativeSDK\/documentation\/MapsNativeSDK\/MapImageSequenceNode","doc:\/\/MapsNativeSDK\/documentation\/MapsNativeSDK\/MapLayer","doc:\/\/MapsNativeSDK\/documentation\/MapsNativeSDK\/MapNode","doc:\/\/MapsNativeSDK\/documentation\/MapsNativeSDK\/MapNodeAnimation","doc:\/\/MapsNativeSDK\/documentation\/MapsNativeSDK\/MapNodeImage","doc:\/\/MapsNativeSDK\/documentation\/MapsNativeSDK\/MapNodeImageSequence","doc:\/\/MapsNativeSDK\/documentation\/MapsNativeSDK\/MapObjectStorage","doc:\/\/MapsNativeSDK\/documentation\/MapsNativeSDK\/MapPin","doc:\/\/MapsNativeSDK\/documentation\/MapsNativeSDK\/MapScene","doc:\/\/MapsNativeSDK\/documentation\/MapsNativeSDK\/MapTextNode","doc:\/\/MapsNativeSDK\/documentation\/MapsNativeSDK\/MapView","doc:\/\/MapsNativeSDK\/documentation\/MapsNativeSDK\/OverlayController","doc:\/\/MapsNativeSDK\/documentation\/MapsNativeSDK\/UserPointerController"]},{"anchor":"Protocols","generated":true,"title":"Protocols","identifiers":["doc:\/\/MapsNativeSDK\/documentation\/MapsNativeSDK\/JSON","doc:\/\/MapsNativeSDK\/documentation\/MapsNativeSDK\/MapAnchoredNode","doc:\/\/MapsNativeSDK\/documentation\/MapsNativeSDK\/MapAsset","doc:\/\/MapsNativeSDK\/documentation\/MapsNativeSDK\/MapBaseNode","doc:\/\/MapsNativeSDK\/documentation\/MapsNativeSDK\/MapSharedObject","doc:\/\/MapsNativeSDK\/documentation\/MapsNativeSDK\/MapViewDelegate","doc:\/\/MapsNativeSDK\/documentation\/MapsNativeSDK\/PaintProperties"]},{"anchor":"Structures","generated":true,"title":"Structures","identifiers":["doc:\/\/MapsNativeSDK\/documentation\/MapsNativeSDK\/Angle","doc:\/\/MapsNativeSDK\/documentation\/MapsNativeSDK\/Coordinates","doc:\/\/MapsNativeSDK\/documentation\/MapsNativeSDK\/CurrentLocationColors","doc:\/\/MapsNativeSDK\/documentation\/MapsNativeSDK\/CurrentLocationModel","doc:\/\/MapsNativeSDK\/documentation\/MapsNativeSDK\/DiskCacheOptions","doc:\/\/MapsNativeSDK\/documentation\/MapsNativeSDK\/FillPaintProperties","doc:\/\/MapsNativeSDK\/documentation\/MapsNativeSDK\/LayoutProperties","doc:\/\/MapsNativeSDK\/documentation\/MapsNativeSDK\/LineDashes","doc:\/\/MapsNativeSDK\/documentation\/MapsNativeSDK\/LinePaintProperties","doc:\/\/MapsNativeSDK\/documentation\/MapsNativeSDK\/MapAnimationOptions","doc:\/\/MapsNativeSDK\/documentation\/MapsNativeSDK\/MapBounds","doc:\/\/MapsNativeSDK\/documentation\/MapsNativeSDK\/MapCameraOptions","doc:\/\/MapsNativeSDK\/documentation\/MapsNativeSDK\/MapConfiguration","doc:\/\/MapsNativeSDK\/documentation\/MapsNativeSDK\/MapImage","doc:\/\/MapsNativeSDK\/documentation\/MapsNativeSDK\/MapNodePoint","doc:\/\/MapsNativeSDK\/documentation\/MapsNativeSDK\/MapStyle","doc:\/\/MapsNativeSDK\/documentation\/MapsNativeSDK\/Marker","doc:\/\/MapsNativeSDK\/documentation\/MapsNativeSDK\/MarkerImageAlignment"]},{"anchor":"Type-Aliases","generated":true,"title":"Type Aliases","identifiers":["doc:\/\/MapsNativeSDK\/documentation\/MapsNativeSDK\/MapEdgeInsets","doc:\/\/MapsNativeSDK\/documentation\/MapsNativeSDK\/PlatformColor","doc:\/\/MapsNativeSDK\/documentation\/MapsNativeSDK\/PlatformImage","doc:\/\/MapsNativeSDK\/documentation\/MapsNativeSDK\/PlatformView"]},{"anchor":"Enumerations","generated":true,"title":"Enumerations","identifiers":["doc:\/\/MapsNativeSDK\/documentation\/MapsNativeSDK\/FeaturesSelectionMode","doc:\/\/MapsNativeSDK\/documentation\/MapsNativeSDK\/MapAnimationEasing","doc:\/\/MapsNativeSDK\/documentation\/MapsNativeSDK\/MapCameraAnimationResult","doc:\/\/MapsNativeSDK\/documentation\/MapsNativeSDK\/MapCameraCoordinates","doc:\/\/MapsNativeSDK\/documentation\/MapsNativeSDK\/MapError","doc:\/\/MapsNativeSDK\/documentation\/MapsNativeSDK\/MapEvent","doc:\/\/MapsNativeSDK\/documentation\/MapsNativeSDK\/MapFeatureId","doc:\/\/MapsNativeSDK\/documentation\/MapsNativeSDK\/MapLogoAlignment","doc:\/\/MapsNativeSDK\/documentation\/MapsNativeSDK\/MapMode","doc:\/\/MapsNativeSDK\/documentation\/MapsNativeSDK\/MapNodeAction","doc:\/\/MapsNativeSDK\/documentation\/MapsNativeSDK\/MapNodeActionAnimationEasing","doc:\/\/MapsNativeSDK\/documentation\/MapsNativeSDK\/MapNodeActionCountMode","doc:\/\/MapsNativeSDK\/documentation\/MapsNativeSDK\/MapPinNode","doc:\/\/MapsNativeSDK\/documentation\/MapsNativeSDK\/MapPredefinedStyle","doc:\/\/MapsNativeSDK\/documentation\/MapsNativeSDK\/MapsNativeStyleError","doc:\/\/MapsNativeSDK\/documentation\/MapsNativeSDK\/MapsSDKConfigurator","doc:\/\/MapsNativeSDK\/documentation\/MapsNativeSDK\/MarkersOverlapMode","doc:\/\/MapsNativeSDK\/documentation\/MapsNativeSDK\/PaintColor","doc:\/\/MapsNativeSDK\/documentation\/MapsNativeSDK\/PaintOpacity","doc:\/\/MapsNativeSDK\/documentation\/MapsNativeSDK\/RenderingType"]},{"anchor":"Extended-Modules","generated":true,"title":"Extended Modules","identifiers":["doc:\/\/MapsNativeSDK\/documentation\/MapsNativeSDK\/CoreBridge","doc:\/\/MapsNativeSDK\/documentation\/MapsNativeSDK\/CoreFoundation","doc:\/\/MapsNativeSDK\/documentation\/MapsNativeSDK\/CoreGraphics","doc:\/\/MapsNativeSDK\/documentation\/MapsNativeSDK\/Foundation","doc:\/\/MapsNativeSDK\/documentation\/MapsNativeSDK\/MapsNativeBridge","doc:\/\/MapsNativeSDK\/documentation\/MapsNativeSDK\/SwiftUICore"]}],"primaryContentSections":[{"kind":"content","content":[{"text":"Обзор","type":"heading","level":2,"anchor":"%D0%9E%D0%B1%D0%B7%D0%BE%D1%80"},{"inlineContent":[{"type":"text","text":"С помощью MapsNativeSDK вы можете добавить в собственное приложение, основанная на AppKit, UIKit или SwiftUI, карты на основе геоданных VK. MapsNativeSDK максимально упрощает процесс интеграции и отображения карт, берет на себя вопросы перемещения камеры по карте и обработку жестов пользователя."}],"type":"paragraph"},{"inlineContent":[{"type":"text","text":"Так же у вас есть возможность добавить на карту произвольные маркеры, полилинии и другие графические элементы, которые позволят пользователю получить дополнительную информацию и успешно взаимодействовать с картой."}],"type":"paragraph"},{"style":"important","name":"Important","type":"aside","content":[{"type":"paragraph","inlineContent":[{"type":"text","text":"Для использования MapsSDK вам необходим API-ключ. Подробнее о том, как его получить вы можете прочитать "},{"isActive":true,"type":"reference","identifier":"https:\/\/dev.vk.com\/ru\/vkmaps\/general-information\/api-key"}]}]},{"text":"Интеграция в приложения","type":"heading","level":2,"anchor":"%D0%98%D0%BD%D1%82%D0%B5%D0%B3%D1%80%D0%B0%D1%86%D0%B8%D1%8F-%D0%B2-%D0%BF%D1%80%D0%B8%D0%BB%D0%BE%D0%B6%D0%B5%D0%BD%D0%B8%D1%8F"},{"items":["doc:\/\/MapsNativeSDK\/documentation\/MapsNativeSDK\/UpdateSdk","doc:\/\/MapsNativeSDK\/documentation\/MapsNativeSDK\/StartUsing"],"style":"detailedGrid","type":"links"},{"text":"Начало использования","type":"heading","level":2,"anchor":"%D0%9D%D0%B0%D1%87%D0%B0%D0%BB%D0%BE-%D0%B8%D1%81%D0%BF%D0%BE%D0%BB%D1%8C%D0%B7%D0%BE%D0%B2%D0%B0%D0%BD%D0%B8%D1%8F"},{"inlineContent":[{"type":"text","text":"Начните знакомство с возможностями MapsNativeSDK со следующей статьи"}],"type":"paragraph"},{"items":["doc:\/\/MapsNativeSDK\/documentation\/MapsNativeSDK\/BaseConcepts"],"style":"detailedGrid","type":"links"}]}],"hierarchy":{"paths":[[]]},"sections":[],"kind":"symbol","metadata":{"roleHeading":"Framework","title":"MapsNativeSDK","modules":[{"name":"MapsNativeSDK"}],"role":"collection","externalID":"MapsNativeSDK","symbolKind":"module"},"abstract":[{"inlineContent":[{"type":"text","text":"MapsNativeSDK"}],"type":"strong"},{"type":"text","text":" - библиотека, позволяющая использовать картографические данные и геосервисы VK в ваших iOS-приложениях."}],"variants":[{"traits":[{"interfaceLanguage":"swift"}],"paths":["\/documentation\/mapsnativesdk"]}],"identifier":{"url":"doc:\/\/MapsNativeSDK\/documentation\/MapsNativeSDK","interfaceLanguage":"swift"},"schemaVersion":{"major":0,"minor":3,"patch":0},"references":{"doc://MapsNativeSDK/documentation/MapsNativeSDK/MapView":{"role":"symbol","title":"MapView","kind":"symbol","identifier":"doc:\/\/MapsNativeSDK\/documentation\/MapsNativeSDK\/MapView","fragments":[{"text":"class","kind":"keyword"},{"text":" ","kind":"text"},{"text":"MapView","kind":"identifier"}],"url":"\/documentation\/mapsnativesdk\/mapview","navigatorTitle":[{"text":"MapView","kind":"identifier"}],"type":"topic","abstract":[{"type":"text","text":"Main object of the Map"}]},"doc://MapsNativeSDK/documentation/MapsNativeSDK/MapCameraCoordinates":{"abstract":[],"navigatorTitle":[{"text":"MapCameraCoordinates","kind":"identifier"}],"url":"\/documentation\/mapsnativesdk\/mapcameracoordinates","role":"symbol","kind":"symbol","fragments":[{"text":"enum","kind":"keyword"},{"text":" ","kind":"text"},{"text":"MapCameraCoordinates","kind":"identifier"}],"identifier":"doc:\/\/MapsNativeSDK\/documentation\/MapsNativeSDK\/MapCameraCoordinates","title":"MapCameraCoordinates","type":"topic"},"doc://MapsNativeSDK/documentation/MapsNativeSDK/CameraController":{"identifier":"doc:\/\/MapsNativeSDK\/documentation\/MapsNativeSDK\/CameraController","navigatorTitle":[{"kind":"identifier","text":"CameraController"}],"title":"CameraController","fragments":[{"kind":"keyword","text":"class"},{"kind":"text","text":" "},{"kind":"identifier","text":"CameraController"}],"type":"topic","role":"symbol","kind":"symbol","url":"\/documentation\/mapsnativesdk\/cameracontroller","abstract":[{"text":"Controller of map camera","type":"text"}]},"doc://MapsNativeSDK/documentation/MapsNativeSDK/MapPredefinedStyle":{"identifier":"doc:\/\/MapsNativeSDK\/documentation\/MapsNativeSDK\/MapPredefinedStyle","role":"symbol","title":"MapPredefinedStyle","fragments":[{"text":"enum","kind":"keyword"},{"text":" ","kind":"text"},{"text":"MapPredefinedStyle","kind":"identifier"}],"type":"topic","url":"\/documentation\/mapsnativesdk\/mappredefinedstyle","abstract":[],"navigatorTitle":[{"text":"MapPredefinedStyle","kind":"identifier"}],"kind":"symbol"},"doc://MapsNativeSDK/documentation/MapsNativeSDK/MarkersOverlapMode":{"url":"\/documentation\/mapsnativesdk\/markersoverlapmode","title":"MarkersOverlapMode","abstract":[],"fragments":[{"text":"enum","kind":"keyword"},{"text":" ","kind":"text"},{"text":"MarkersOverlapMode","kind":"identifier"}],"navigatorTitle":[{"text":"MarkersOverlapMode","kind":"identifier"}],"kind":"symbol","identifier":"doc:\/\/MapsNativeSDK\/documentation\/MapsNativeSDK\/MarkersOverlapMode","type":"topic","role":"symbol"},"doc://MapsNativeSDK/documentation/MapsNativeSDK/CameraMoving":{"role":"article","abstract":[{"type":"text","text":"Изменяйте положение камеры в пространстве, управляя ее координатами, уровнем увеличения, наклоном, поворотом и другими параметрами."}],"type":"topic","url":"\/documentation\/mapsnativesdk\/cameramoving","title":"Управление камерой","identifier":"doc:\/\/MapsNativeSDK\/documentation\/MapsNativeSDK\/CameraMoving","kind":"article"},"doc://MapsNativeSDK/documentation/MapsNativeSDK/MapsSDKConfigurator":{"abstract":[{"type":"text","text":"Configurator of SDK"}],"title":"MapsSDKConfigurator","fragments":[{"text":"enum","kind":"keyword"},{"text":" ","kind":"text"},{"text":"MapsSDKConfigurator","kind":"identifier"}],"navigatorTitle":[{"text":"MapsSDKConfigurator","kind":"identifier"}],"role":"symbol","type":"topic","kind":"symbol","identifier":"doc:\/\/MapsNativeSDK\/documentation\/MapsNativeSDK\/MapsSDKConfigurator","url":"\/documentation\/mapsnativesdk\/mapssdkconfigurator"},"doc://MapsNativeSDK/documentation/MapsNativeSDK/Styles":{"title":"Оформление карты","kind":"article","identifier":"doc:\/\/MapsNativeSDK\/documentation\/MapsNativeSDK\/Styles","abstract":[{"text":"Изменяйте внешний вид карты, рисуйте геометрические фигуры и размещайте маркеры.","type":"text"}],"type":"topic","role":"article","url":"\/documentation\/mapsnativesdk\/styles"},"doc://MapsNativeSDK/documentation/MapsNativeSDK/PlatformView":{"kind":"symbol","title":"PlatformView","navigatorTitle":[{"text":"PlatformView","kind":"identifier"}],"url":"\/documentation\/mapsnativesdk\/platformview","identifier":"doc:\/\/MapsNativeSDK\/documentation\/MapsNativeSDK\/PlatformView","type":"topic","abstract":[],"role":"symbol","fragments":[{"text":"typealias","kind":"keyword"},{"text":" ","kind":"text"},{"text":"PlatformView","kind":"identifier"}]},"doc://MapsNativeSDK/documentation/MapsNativeSDK/MapNodePoint":{"abstract":[],"type":"topic","navigatorTitle":[{"kind":"identifier","text":"MapNodePoint"}],"url":"\/documentation\/mapsnativesdk\/mapnodepoint","title":"MapNodePoint","kind":"symbol","role":"symbol","fragments":[{"kind":"keyword","text":"struct"},{"kind":"text","text":" "},{"kind":"identifier","text":"MapNodePoint"}],"identifier":"doc:\/\/MapsNativeSDK\/documentation\/MapsNativeSDK\/MapNodePoint"},"https://dev.vk.com/ru/vkmaps/general-information/api-key":{"title":"по этой ссылке","identifier":"https:\/\/dev.vk.com\/ru\/vkmaps\/general-information\/api-key","titleInlineContent":[{"type":"text","text":"по этой ссылке"}],"url":"https:\/\/dev.vk.com\/ru\/vkmaps\/general-information\/api-key","type":"link"},"doc://MapsNativeSDK/documentation/MapsNativeSDK/MapImageNode":{"identifier":"doc:\/\/MapsNativeSDK\/documentation\/MapsNativeSDK\/MapImageNode","url":"\/documentation\/mapsnativesdk\/mapimagenode","kind":"symbol","role":"symbol","fragments":[{"text":"class","kind":"keyword"},{"text":" ","kind":"text"},{"text":"MapImageNode","kind":"identifier"}],"navigatorTitle":[{"text":"MapImageNode","kind":"identifier"}],"title":"MapImageNode","type":"topic","abstract":[]},"doc://MapsNativeSDK/documentation/MapsNativeSDK/FillPaintProperties":{"role":"symbol","navigatorTitle":[{"kind":"identifier","text":"FillPaintProperties"}],"identifier":"doc:\/\/MapsNativeSDK\/documentation\/MapsNativeSDK\/FillPaintProperties","abstract":[],"kind":"symbol","type":"topic","title":"FillPaintProperties","fragments":[{"kind":"keyword","text":"struct"},{"kind":"text","text":" "},{"kind":"identifier","text":"FillPaintProperties"}],"url":"\/documentation\/mapsnativesdk\/fillpaintproperties"},"doc://MapsNativeSDK/documentation/MapsNativeSDK/PaintOpacity":{"abstract":[],"title":"PaintOpacity","kind":"symbol","navigatorTitle":[{"kind":"identifier","text":"PaintOpacity"}],"role":"symbol","fragments":[{"kind":"keyword","text":"enum"},{"kind":"text","text":" "},{"kind":"identifier","text":"PaintOpacity"}],"identifier":"doc:\/\/MapsNativeSDK\/documentation\/MapsNativeSDK\/PaintOpacity","type":"topic","url":"\/documentation\/mapsnativesdk\/paintopacity"},"doc://MapsNativeSDK/documentation/MapsNativeSDK/Markers":{"identifier":"doc:\/\/MapsNativeSDK\/documentation\/MapsNativeSDK\/Markers","abstract":[{"text":"Размещайте на карте маркеры для индикации конкретных мест на карте.","type":"text"}],"url":"\/documentation\/mapsnativesdk\/markers","kind":"article","type":"topic","role":"article","title":"Маркеры"},"doc://MapsNativeSDK/documentation/MapsNativeSDK/LayoutProperties":{"identifier":"doc:\/\/MapsNativeSDK\/documentation\/MapsNativeSDK\/LayoutProperties","abstract":[],"url":"\/documentation\/mapsnativesdk\/layoutproperties","title":"LayoutProperties","kind":"symbol","role":"symbol","type":"topic","fragments":[{"text":"struct","kind":"keyword"},{"text":" ","kind":"text"},{"text":"LayoutProperties","kind":"identifier"}],"navigatorTitle":[{"kind":"identifier","text":"LayoutProperties"}]},"doc://MapsNativeSDK/documentation/MapsNativeSDK/MapObjectStorage":{"abstract":[],"identifier":"doc:\/\/MapsNativeSDK\/documentation\/MapsNativeSDK\/MapObjectStorage","fragments":[{"text":"class","kind":"keyword"},{"text":" ","kind":"text"},{"text":"MapObjectStorage","kind":"identifier"}],"navigatorTitle":[{"text":"MapObjectStorage","kind":"identifier"}],"url":"\/documentation\/mapsnativesdk\/mapobjectstorage","kind":"symbol","role":"symbol","title":"MapObjectStorage","type":"topic"},"doc://MapsNativeSDK/documentation/MapsNativeSDK/StartUsing":{"abstract":[{"text":"Интегрируйте карты в свое приложение на основе UIKit или SwiftUI.","type":"text"}],"title":"Начало работы с MapsNativeSDK","kind":"article","identifier":"doc:\/\/MapsNativeSDK\/documentation\/MapsNativeSDK\/StartUsing","role":"article","type":"topic","url":"\/documentation\/mapsnativesdk\/startusing"},"doc://MapsNativeSDK/documentation/MapsNativeSDK/BaseConcepts":{"identifier":"doc:\/\/MapsNativeSDK\/documentation\/MapsNativeSDK\/BaseConcepts","title":"Базовые возможности MapsNativeSDK","url":"\/documentation\/mapsnativesdk\/baseconcepts","type":"topic","role":"article","abstract":[{"text":"Кратко рассмотрим основные понятия и возможности, доступные вам при использовании MapsNativeSDK.","type":"text"}],"kind":"article"},"doc://MapsNativeSDK/documentation/MapsNativeSDK/MapsNativeBridge":{"type":"topic","kind":"symbol","url":"\/documentation\/mapsnativesdk\/mapsnativebridge","title":"MapsNativeBridge","abstract":[],"role":"collection","identifier":"doc:\/\/MapsNativeSDK\/documentation\/MapsNativeSDK\/MapsNativeBridge"},"doc://MapsNativeSDK/documentation/MapsNativeSDK/MapLogoAlignment":{"abstract":[],"url":"\/documentation\/mapsnativesdk\/maplogoalignment","kind":"symbol","role":"symbol","identifier":"doc:\/\/MapsNativeSDK\/documentation\/MapsNativeSDK\/MapLogoAlignment","fragments":[{"text":"enum","kind":"keyword"},{"text":" ","kind":"text"},{"text":"MapLogoAlignment","kind":"identifier"}],"title":"MapLogoAlignment","type":"topic","navigatorTitle":[{"text":"MapLogoAlignment","kind":"identifier"}]},"doc://MapsNativeSDK/documentation/MapsNativeSDK/MapNode":{"fragments":[{"text":"class","kind":"keyword"},{"text":" ","kind":"text"},{"text":"MapNode","kind":"identifier"}],"navigatorTitle":[{"text":"MapNode","kind":"identifier"}],"kind":"symbol","abstract":[],"identifier":"doc:\/\/MapsNativeSDK\/documentation\/MapsNativeSDK\/MapNode","type":"topic","url":"\/documentation\/mapsnativesdk\/mapnode","role":"symbol","title":"MapNode"},"doc://MapsNativeSDK/documentation/MapsNativeSDK/OverlayController":{"navigatorTitle":[{"text":"OverlayController","kind":"identifier"}],"url":"\/documentation\/mapsnativesdk\/overlaycontroller","kind":"symbol","type":"topic","fragments":[{"text":"class","kind":"keyword"},{"text":" ","kind":"text"},{"text":"OverlayController","kind":"identifier"}],"title":"OverlayController","abstract":[{"text":"Controller of the Map’s overlay","type":"text"}],"identifier":"doc:\/\/MapsNativeSDK\/documentation\/MapsNativeSDK\/OverlayController","role":"symbol"},"doc://MapsNativeSDK/documentation/MapsNativeSDK/Marker":{"type":"topic","abstract":[],"identifier":"doc:\/\/MapsNativeSDK\/documentation\/MapsNativeSDK\/Marker","fragments":[{"text":"struct","kind":"keyword"},{"text":" ","kind":"text"},{"text":"Marker","kind":"identifier"}],"navigatorTitle":[{"text":"Marker","kind":"identifier"}],"title":"Marker","kind":"symbol","url":"\/documentation\/mapsnativesdk\/marker","role":"symbol"},"doc://MapsNativeSDK/documentation/MapsNativeSDK/MapSharedObject":{"title":"MapSharedObject","navigatorTitle":[{"kind":"identifier","text":"MapSharedObject"}],"kind":"symbol","role":"symbol","type":"topic","identifier":"doc:\/\/MapsNativeSDK\/documentation\/MapsNativeSDK\/MapSharedObject","url":"\/documentation\/mapsnativesdk\/mapsharedobject","abstract":[],"fragments":[{"kind":"keyword","text":"protocol"},{"kind":"text","text":" "},{"kind":"identifier","text":"MapSharedObject"}]},"doc://MapsNativeSDK/documentation/MapsNativeSDK/MapCameraOptions":{"kind":"symbol","abstract":[{"text":"State of camera, inlcude bearing, zoom, pitch and padding","type":"text"}],"title":"MapCameraOptions","type":"topic","url":"\/documentation\/mapsnativesdk\/mapcameraoptions","fragments":[{"text":"struct","kind":"keyword"},{"text":" ","kind":"text"},{"text":"MapCameraOptions","kind":"identifier"}],"role":"symbol","identifier":"doc:\/\/MapsNativeSDK\/documentation\/MapsNativeSDK\/MapCameraOptions","navigatorTitle":[{"text":"MapCameraOptions","kind":"identifier"}]},"doc://MapsNativeSDK/documentation/MapsNativeSDK/CoreBridge":{"role":"collection","url":"\/documentation\/mapsnativesdk\/corebridge","identifier":"doc:\/\/MapsNativeSDK\/documentation\/MapsNativeSDK\/CoreBridge","abstract":[],"title":"CoreBridge","kind":"symbol","type":"topic"},"doc://MapsNativeSDK/documentation/MapsNativeSDK/Lifecycle":{"abstract":[{"text":"Отслеживайте события, происходящие с картой, и программируйте реакцию на них.","type":"text"}],"kind":"article","title":"Отслеживание событий карты","role":"article","url":"\/documentation\/mapsnativesdk\/lifecycle","type":"topic","identifier":"doc:\/\/MapsNativeSDK\/documentation\/MapsNativeSDK\/Lifecycle"},"doc://MapsNativeSDK/documentation/MapsNativeSDK/MapImage":{"kind":"symbol","title":"MapImage","role":"symbol","type":"topic","fragments":[{"kind":"keyword","text":"struct"},{"kind":"text","text":" "},{"kind":"identifier","text":"MapImage"}],"abstract":[],"identifier":"doc:\/\/MapsNativeSDK\/documentation\/MapsNativeSDK\/MapImage","url":"\/documentation\/mapsnativesdk\/mapimage","navigatorTitle":[{"kind":"identifier","text":"MapImage"}]},"doc://MapsNativeSDK/documentation/MapsNativeSDK/UpdateSdk":{"abstract":[{"type":"text","text":"Сделайте переход со старого JS MapsSDK на MapsNativeSDK максимально просто."}],"role":"article","kind":"article","title":"Переход с JS MapsSDK","type":"topic","url":"\/documentation\/mapsnativesdk\/updatesdk","identifier":"doc:\/\/MapsNativeSDK\/documentation\/MapsNativeSDK\/UpdateSdk"},"doc://MapsNativeSDK/documentation/MapsNativeSDK/RenderingType":{"role":"symbol","identifier":"doc:\/\/MapsNativeSDK\/documentation\/MapsNativeSDK\/RenderingType","navigatorTitle":[{"text":"RenderingType","kind":"identifier"}],"fragments":[{"text":"enum","kind":"keyword"},{"text":" ","kind":"text"},{"text":"RenderingType","kind":"identifier"}],"type":"topic","title":"RenderingType","url":"\/documentation\/mapsnativesdk\/renderingtype","abstract":[],"kind":"symbol"},"doc://MapsNativeSDK/documentation/MapsNativeSDK/MapStyle":{"fragments":[{"text":"struct","kind":"keyword"},{"text":" ","kind":"text"},{"text":"MapStyle","kind":"identifier"}],"navigatorTitle":[{"text":"MapStyle","kind":"identifier"}],"kind":"symbol","url":"\/documentation\/mapsnativesdk\/mapstyle","role":"symbol","title":"MapStyle","abstract":[],"type":"topic","identifier":"doc:\/\/MapsNativeSDK\/documentation\/MapsNativeSDK\/MapStyle"},"doc://MapsNativeSDK/documentation/MapsNativeSDK/MapFeatureId":{"kind":"symbol","abstract":[],"navigatorTitle":[{"kind":"identifier","text":"MapFeatureId"}],"fragments":[{"kind":"keyword","text":"enum"},{"kind":"text","text":" "},{"kind":"identifier","text":"MapFeatureId"}],"title":"MapFeatureId","url":"\/documentation\/mapsnativesdk\/mapfeatureid","type":"topic","identifier":"doc:\/\/MapsNativeSDK\/documentation\/MapsNativeSDK\/MapFeatureId","role":"symbol"},"doc://MapsNativeSDK/documentation/MapsNativeSDK/MapEvent":{"abstract":[{"text":"Event of the Map","type":"text"}],"fragments":[{"text":"enum","kind":"keyword"},{"text":" ","kind":"text"},{"text":"MapEvent","kind":"identifier"}],"title":"MapEvent","kind":"symbol","navigatorTitle":[{"text":"MapEvent","kind":"identifier"}],"url":"\/documentation\/mapsnativesdk\/mapevent","identifier":"doc:\/\/MapsNativeSDK\/documentation\/MapsNativeSDK\/MapEvent","role":"symbol","type":"topic"},"doc://MapsNativeSDK/documentation/MapsNativeSDK/MapCameraAnimationResult":{"url":"\/documentation\/mapsnativesdk\/mapcameraanimationresult","type":"topic","navigatorTitle":[{"text":"MapCameraAnimationResult","kind":"identifier"}],"fragments":[{"text":"enum","kind":"keyword"},{"text":" ","kind":"text"},{"text":"MapCameraAnimationResult","kind":"identifier"}],"abstract":[{"type":"text","text":"Result of the camera animated moving"}],"title":"MapCameraAnimationResult","role":"symbol","identifier":"doc:\/\/MapsNativeSDK\/documentation\/MapsNativeSDK\/MapCameraAnimationResult","kind":"symbol"},"doc://MapsNativeSDK/documentation/MapsNativeSDK/PaintProperties":{"abstract":[],"kind":"symbol","url":"\/documentation\/mapsnativesdk\/paintproperties","navigatorTitle":[{"kind":"identifier","text":"PaintProperties"}],"fragments":[{"kind":"keyword","text":"protocol"},{"kind":"text","text":" "},{"kind":"identifier","text":"PaintProperties"}],"type":"topic","title":"PaintProperties","role":"symbol","identifier":"doc:\/\/MapsNativeSDK\/documentation\/MapsNativeSDK\/PaintProperties"},"doc://MapsNativeSDK/documentation/MapsNativeSDK/MapNodeAnimation":{"kind":"symbol","type":"topic","abstract":[],"url":"\/documentation\/mapsnativesdk\/mapnodeanimation","fragments":[{"text":"class","kind":"keyword"},{"text":" ","kind":"text"},{"text":"MapNodeAnimation","kind":"identifier"}],"role":"symbol","navigatorTitle":[{"text":"MapNodeAnimation","kind":"identifier"}],"identifier":"doc:\/\/MapsNativeSDK\/documentation\/MapsNativeSDK\/MapNodeAnimation","title":"MapNodeAnimation"},"doc://MapsNativeSDK/documentation/MapsNativeSDK/CoreFoundation":{"role":"collection","title":"CoreFoundation","kind":"symbol","identifier":"doc:\/\/MapsNativeSDK\/documentation\/MapsNativeSDK\/CoreFoundation","type":"topic","abstract":[],"url":"\/documentation\/mapsnativesdk\/corefoundation"},"doc://MapsNativeSDK/documentation/MapsNativeSDK/MapScene":{"identifier":"doc:\/\/MapsNativeSDK\/documentation\/MapsNativeSDK\/MapScene","url":"\/documentation\/mapsnativesdk\/mapscene","kind":"symbol","title":"MapScene","type":"topic","role":"symbol","fragments":[{"text":"class","kind":"keyword"},{"text":" ","kind":"text"},{"text":"MapScene","kind":"identifier"}],"navigatorTitle":[{"text":"MapScene","kind":"identifier"}],"abstract":[]},"doc://MapsNativeSDK/documentation/MapsNativeSDK/MapMode":{"abstract":[{"text":"Mode of the Map","type":"text"}],"title":"MapMode","role":"symbol","type":"topic","fragments":[{"text":"enum","kind":"keyword"},{"text":" ","kind":"text"},{"text":"MapMode","kind":"identifier"}],"identifier":"doc:\/\/MapsNativeSDK\/documentation\/MapsNativeSDK\/MapMode","navigatorTitle":[{"text":"MapMode","kind":"identifier"}],"kind":"symbol","url":"\/documentation\/mapsnativesdk\/mapmode"},"doc://MapsNativeSDK/documentation/MapsNativeSDK/MapNodeImage":{"fragments":[{"kind":"keyword","text":"class"},{"kind":"text","text":" "},{"kind":"identifier","text":"MapNodeImage"}],"type":"topic","kind":"symbol","url":"\/documentation\/mapsnativesdk\/mapnodeimage","role":"symbol","title":"MapNodeImage","abstract":[],"identifier":"doc:\/\/MapsNativeSDK\/documentation\/MapsNativeSDK\/MapNodeImage","navigatorTitle":[{"kind":"identifier","text":"MapNodeImage"}]},"doc://MapsNativeSDK/documentation/MapsNativeSDK/FeaturesSelectionMode":{"url":"\/documentation\/mapsnativesdk\/featuresselectionmode","type":"topic","identifier":"doc:\/\/MapsNativeSDK\/documentation\/MapsNativeSDK\/FeaturesSelectionMode","fragments":[{"kind":"keyword","text":"enum"},{"kind":"text","text":" "},{"kind":"identifier","text":"FeaturesSelectionMode"}],"title":"FeaturesSelectionMode","role":"symbol","kind":"symbol","abstract":[],"navigatorTitle":[{"kind":"identifier","text":"FeaturesSelectionMode"}]},"doc://MapsNativeSDK/documentation/MapsNativeSDK/MapImageSequenceNode":{"identifier":"doc:\/\/MapsNativeSDK\/documentation\/MapsNativeSDK\/MapImageSequenceNode","title":"MapImageSequenceNode","abstract":[],"role":"symbol","navigatorTitle":[{"text":"MapImageSequenceNode","kind":"identifier"}],"type":"topic","fragments":[{"text":"class","kind":"keyword"},{"text":" ","kind":"text"},{"text":"MapImageSequenceNode","kind":"identifier"}],"url":"\/documentation\/mapsnativesdk\/mapimagesequencenode","kind":"symbol"},"doc://MapsNativeSDK/documentation/MapsNativeSDK/CurrentLocationModel":{"kind":"symbol","type":"topic","identifier":"doc:\/\/MapsNativeSDK\/documentation\/MapsNativeSDK\/CurrentLocationModel","url":"\/documentation\/mapsnativesdk\/currentlocationmodel","role":"symbol","navigatorTitle":[{"text":"CurrentLocationModel","kind":"identifier"}],"title":"CurrentLocationModel","abstract":[],"fragments":[{"text":"struct","kind":"keyword"},{"text":" ","kind":"text"},{"text":"CurrentLocationModel","kind":"identifier"}]},"doc://MapsNativeSDK/documentation/MapsNativeSDK/MapAnimationOptions":{"abstract":[],"url":"\/documentation\/mapsnativesdk\/mapanimationoptions","kind":"symbol","role":"symbol","identifier":"doc:\/\/MapsNativeSDK\/documentation\/MapsNativeSDK\/MapAnimationOptions","fragments":[{"text":"struct","kind":"keyword"},{"kind":"text","text":" "},{"kind":"identifier","text":"MapAnimationOptions"}],"type":"topic","title":"MapAnimationOptions","navigatorTitle":[{"kind":"identifier","text":"MapAnimationOptions"}]},"doc://MapsNativeSDK/documentation/MapsNativeSDK/JSON":{"navigatorTitle":[{"kind":"identifier","text":"JSON"}],"type":"topic","role":"symbol","kind":"symbol","identifier":"doc:\/\/MapsNativeSDK\/documentation\/MapsNativeSDK\/JSON","title":"JSON","fragments":[{"kind":"keyword","text":"protocol"},{"kind":"text","text":" "},{"kind":"identifier","text":"JSON"}],"abstract":[],"url":"\/documentation\/mapsnativesdk\/json"},"doc://MapsNativeSDK/documentation/MapsNativeSDK/MapConfiguration":{"url":"\/documentation\/mapsnativesdk\/mapconfiguration","type":"topic","role":"symbol","kind":"symbol","navigatorTitle":[{"text":"MapConfiguration","kind":"identifier"}],"title":"MapConfiguration","abstract":[{"type":"text","text":"Configuration of Map"}],"identifier":"doc:\/\/MapsNativeSDK\/documentation\/MapsNativeSDK\/MapConfiguration","fragments":[{"text":"struct","kind":"keyword"},{"text":" ","kind":"text"},{"text":"MapConfiguration","kind":"identifier"}]},"doc://MapsNativeSDK/documentation/MapsNativeSDK/PlatformColor":{"role":"symbol","navigatorTitle":[{"text":"PlatformColor","kind":"identifier"}],"title":"PlatformColor","identifier":"doc:\/\/MapsNativeSDK\/documentation\/MapsNativeSDK\/PlatformColor","kind":"symbol","url":"\/documentation\/mapsnativesdk\/platformcolor","abstract":[],"type":"topic","fragments":[{"text":"typealias","kind":"keyword"},{"text":" ","kind":"text"},{"text":"PlatformColor","kind":"identifier"}]},"doc://MapsNativeSDK/documentation/MapsNativeSDK/MapsNativeStyleError":{"identifier":"doc:\/\/MapsNativeSDK\/documentation\/MapsNativeSDK\/MapsNativeStyleError","fragments":[{"kind":"keyword","text":"enum"},{"kind":"text","text":" "},{"kind":"identifier","text":"MapsNativeStyleError"}],"kind":"symbol","navigatorTitle":[{"kind":"identifier","text":"MapsNativeStyleError"}],"title":"MapsNativeStyleError","type":"topic","abstract":[],"url":"\/documentation\/mapsnativesdk\/mapsnativestyleerror","role":"symbol"},"doc://MapsNativeSDK/documentation/MapsNativeSDK/LineDashes":{"kind":"symbol","navigatorTitle":[{"text":"LineDashes","kind":"identifier"}],"url":"\/documentation\/mapsnativesdk\/linedashes","fragments":[{"text":"struct","kind":"keyword"},{"text":" ","kind":"text"},{"text":"LineDashes","kind":"identifier"}],"title":"LineDashes","role":"symbol","identifier":"doc:\/\/MapsNativeSDK\/documentation\/MapsNativeSDK\/LineDashes","abstract":[],"type":"topic"},"doc://MapsNativeSDK/documentation/MapsNativeSDK/MapTextNode":{"title":"MapTextNode","abstract":[],"kind":"symbol","fragments":[{"text":"class","kind":"keyword"},{"text":" ","kind":"text"},{"text":"MapTextNode","kind":"identifier"}],"type":"topic","role":"symbol","url":"\/documentation\/mapsnativesdk\/maptextnode","identifier":"doc:\/\/MapsNativeSDK\/documentation\/MapsNativeSDK\/MapTextNode","navigatorTitle":[{"text":"MapTextNode","kind":"identifier"}]},"doc://MapsNativeSDK/documentation/MapsNativeSDK/MapNodeActionCountMode":{"type":"topic","url":"\/documentation\/mapsnativesdk\/mapnodeactioncountmode","abstract":[],"kind":"symbol","fragments":[{"kind":"keyword","text":"enum"},{"kind":"text","text":" "},{"kind":"identifier","text":"MapNodeActionCountMode"}],"navigatorTitle":[{"kind":"identifier","text":"MapNodeActionCountMode"}],"identifier":"doc:\/\/MapsNativeSDK\/documentation\/MapsNativeSDK\/MapNodeActionCountMode","title":"MapNodeActionCountMode","role":"symbol"},"doc://MapsNativeSDK/documentation/MapsNativeSDK/MapEdgeInsets":{"fragments":[{"text":"typealias","kind":"keyword"},{"text":" ","kind":"text"},{"kind":"identifier","text":"MapEdgeInsets"}],"navigatorTitle":[{"kind":"identifier","text":"MapEdgeInsets"}],"kind":"symbol","abstract":[],"identifier":"doc:\/\/MapsNativeSDK\/documentation\/MapsNativeSDK\/MapEdgeInsets","type":"topic","url":"\/documentation\/mapsnativesdk\/mapedgeinsets","role":"symbol","title":"MapEdgeInsets"},"doc://MapsNativeSDK/documentation/MapsNativeSDK/UserPointerController":{"identifier":"doc:\/\/MapsNativeSDK\/documentation\/MapsNativeSDK\/UserPointerController","title":"UserPointerController","kind":"symbol","role":"symbol","navigatorTitle":[{"text":"UserPointerController","kind":"identifier"}],"abstract":[],"type":"topic","url":"\/documentation\/mapsnativesdk\/userpointercontroller","fragments":[{"text":"class","kind":"keyword"},{"text":" ","kind":"text"},{"text":"UserPointerController","kind":"identifier"}]},"doc://MapsNativeSDK/documentation/MapsNativeSDK/PlatformImage":{"role":"symbol","type":"topic","url":"\/documentation\/mapsnativesdk\/platformimage","title":"PlatformImage","navigatorTitle":[{"text":"PlatformImage","kind":"identifier"}],"kind":"symbol","abstract":[],"identifier":"doc:\/\/MapsNativeSDK\/documentation\/MapsNativeSDK\/PlatformImage","fragments":[{"text":"typealias","kind":"keyword"},{"text":" ","kind":"text"},{"text":"PlatformImage","kind":"identifier"}]},"doc://MapsNativeSDK/documentation/MapsNativeSDK/MapBounds":{"kind":"symbol","role":"symbol","url":"\/documentation\/mapsnativesdk\/mapbounds","fragments":[{"text":"struct","kind":"keyword"},{"text":" ","kind":"text"},{"text":"MapBounds","kind":"identifier"}],"identifier":"doc:\/\/MapsNativeSDK\/documentation\/MapsNativeSDK\/MapBounds","abstract":[],"navigatorTitle":[{"text":"MapBounds","kind":"identifier"}],"title":"MapBounds","type":"topic"},"doc://MapsNativeSDK/documentation/MapsNativeSDK/MapAsset":{"kind":"symbol","identifier":"doc:\/\/MapsNativeSDK\/documentation\/MapsNativeSDK\/MapAsset","type":"topic","title":"MapAsset","navigatorTitle":[{"kind":"identifier","text":"MapAsset"}],"abstract":[],"fragments":[{"kind":"keyword","text":"protocol"},{"kind":"text","text":" "},{"kind":"identifier","text":"MapAsset"}],"url":"\/documentation\/mapsnativesdk\/mapasset","role":"symbol"},"doc://MapsNativeSDK/documentation/MapsNativeSDK/MapLayer":{"fragments":[{"kind":"keyword","text":"class"},{"kind":"text","text":" "},{"kind":"identifier","text":"MapLayer"}],"title":"MapLayer","url":"\/documentation\/mapsnativesdk\/maplayer","type":"topic","role":"symbol","navigatorTitle":[{"kind":"identifier","text":"MapLayer"}],"identifier":"doc:\/\/MapsNativeSDK\/documentation\/MapsNativeSDK\/MapLayer","kind":"symbol","abstract":[]},"doc://MapsNativeSDK/documentation/MapsNativeSDK":{"url":"\/documentation\/mapsnativesdk","title":"MapsNativeSDK","kind":"symbol","type":"topic","role":"collection","abstract":[{"inlineContent":[{"type":"text","text":"MapsNativeSDK"}],"type":"strong"},{"type":"text","text":" - библиотека, позволяющая использовать картографические данные и геосервисы VK в ваших iOS-приложениях."}],"identifier":"doc:\/\/MapsNativeSDK\/documentation\/MapsNativeSDK"},"doc://MapsNativeSDK/documentation/MapsNativeSDK/MapPin":{"abstract":[],"identifier":"doc:\/\/MapsNativeSDK\/documentation\/MapsNativeSDK\/MapPin","fragments":[{"text":"class","kind":"keyword"},{"text":" ","kind":"text"},{"text":"MapPin","kind":"identifier"}],"navigatorTitle":[{"text":"MapPin","kind":"identifier"}],"url":"\/documentation\/mapsnativesdk\/mappin","kind":"symbol","role":"symbol","title":"MapPin","type":"topic"},"doc://MapsNativeSDK/documentation/MapsNativeSDK/MapViewDelegate":{"navigatorTitle":[{"text":"MapViewDelegate","kind":"identifier"}],"role":"symbol","abstract":[{"type":"text","text":"Interface, that MapView uses to inform its delegate about events on map"}],"url":"\/documentation\/mapsnativesdk\/mapviewdelegate","type":"topic","fragments":[{"text":"protocol","kind":"keyword"},{"text":" ","kind":"text"},{"text":"MapViewDelegate","kind":"identifier"}],"kind":"symbol","identifier":"doc:\/\/MapsNativeSDK\/documentation\/MapsNativeSDK\/MapViewDelegate","title":"MapViewDelegate"},"doc://MapsNativeSDK/documentation/MapsNativeSDK/MapNodeAction":{"abstract":[],"identifier":"doc:\/\/MapsNativeSDK\/documentation\/MapsNativeSDK\/MapNodeAction","type":"topic","fragments":[{"text":"enum","kind":"keyword"},{"text":" ","kind":"text"},{"text":"MapNodeAction","kind":"identifier"}],"title":"MapNodeAction","kind":"symbol","url":"\/documentation\/mapsnativesdk\/mapnodeaction","navigatorTitle":[{"text":"MapNodeAction","kind":"identifier"}],"role":"symbol"},"doc://MapsNativeSDK/documentation/MapsNativeSDK/MapAnchoredNode":{"kind":"symbol","role":"symbol","navigatorTitle":[{"text":"MapAnchoredNode","kind":"identifier"}],"url":"\/documentation\/mapsnativesdk\/mapanchorednode","fragments":[{"text":"protocol","kind":"keyword"},{"text":" ","kind":"text"},{"text":"MapAnchoredNode","kind":"identifier"}],"type":"topic","identifier":"doc:\/\/MapsNativeSDK\/documentation\/MapsNativeSDK\/MapAnchoredNode","abstract":[],"title":"MapAnchoredNode"},"doc://MapsNativeSDK/documentation/MapsNativeSDK/Controls":{"type":"topic","kind":"article","role":"article","identifier":"doc:\/\/MapsNativeSDK\/documentation\/MapsNativeSDK\/Controls","url":"\/documentation\/mapsnativesdk\/controls","abstract":[{"type":"text","text":"Используйте встроенные в SDK элементы управления или реализуйте собственные."}],"title":"Элементы управления картой"},"doc://MapsNativeSDK/documentation/MapsNativeSDK/Gestures":{"type":"topic","role":"article","title":"Жесты","kind":"article","abstract":[{"type":"text","text":"Управляйте картой с помощью широкого списка доступных жестов."}],"identifier":"doc:\/\/MapsNativeSDK\/documentation\/MapsNativeSDK\/Gestures","url":"\/documentation\/mapsnativesdk\/gestures"},"doc://MapsNativeSDK/documentation/MapsNativeSDK/LinePaintProperties":{"kind":"symbol","role":"symbol","title":"LinePaintProperties","navigatorTitle":[{"kind":"identifier","text":"LinePaintProperties"}],"type":"topic","identifier":"doc:\/\/MapsNativeSDK\/documentation\/MapsNativeSDK\/LinePaintProperties","url":"\/documentation\/mapsnativesdk\/linepaintproperties","abstract":[],"fragments":[{"kind":"keyword","text":"struct"},{"kind":"text","text":" "},{"kind":"identifier","text":"LinePaintProperties"}]},"doc://MapsNativeSDK/documentation/MapsNativeSDK/DiskCacheOptions":{"navigatorTitle":[{"text":"DiskCacheOptions","kind":"identifier"}],"url":"\/documentation\/mapsnativesdk\/diskcacheoptions","type":"topic","role":"symbol","fragments":[{"text":"struct","kind":"keyword"},{"text":" ","kind":"text"},{"text":"DiskCacheOptions","kind":"identifier"}],"abstract":[],"identifier":"doc:\/\/MapsNativeSDK\/documentation\/MapsNativeSDK\/DiskCacheOptions","kind":"symbol","title":"DiskCacheOptions"},"doc://MapsNativeSDK/documentation/MapsNativeSDK/MapNodeImageSequence":{"title":"MapNodeImageSequence","type":"topic","url":"\/documentation\/mapsnativesdk\/mapnodeimagesequence","fragments":[{"text":"class","kind":"keyword"},{"text":" ","kind":"text"},{"text":"MapNodeImageSequence","kind":"identifier"}],"navigatorTitle":[{"text":"MapNodeImageSequence","kind":"identifier"}],"identifier":"doc:\/\/MapsNativeSDK\/documentation\/MapsNativeSDK\/MapNodeImageSequence","abstract":[],"kind":"symbol","role":"symbol"},"doc://MapsNativeSDK/documentation/MapsNativeSDK/MarkerImageAlignment":{"title":"MarkerImageAlignment","kind":"symbol","role":"symbol","fragments":[{"text":"struct","kind":"keyword"},{"text":" ","kind":"text"},{"text":"MarkerImageAlignment","kind":"identifier"}],"type":"topic","abstract":[],"url":"\/documentation\/mapsnativesdk\/markerimagealignment","navigatorTitle":[{"text":"MarkerImageAlignment","kind":"identifier"}],"identifier":"doc:\/\/MapsNativeSDK\/documentation\/MapsNativeSDK\/MarkerImageAlignment"},"doc://MapsNativeSDK/documentation/MapsNativeSDK/MapPinNode":{"kind":"symbol","title":"MapPinNode","abstract":[],"identifier":"doc:\/\/MapsNativeSDK\/documentation\/MapsNativeSDK\/MapPinNode","role":"symbol","fragments":[{"kind":"keyword","text":"enum"},{"kind":"text","text":" "},{"kind":"identifier","text":"MapPinNode"}],"navigatorTitle":[{"kind":"identifier","text":"MapPinNode"}],"type":"topic","url":"\/documentation\/mapsnativesdk\/mappinnode"},"doc://MapsNativeSDK/documentation/MapsNativeSDK/MapDataSource":{"navigatorTitle":[{"text":"MapDataSource","kind":"identifier"}],"identifier":"doc:\/\/MapsNativeSDK\/documentation\/MapsNativeSDK\/MapDataSource","role":"symbol","abstract":[],"url":"\/documentation\/mapsnativesdk\/mapdatasource","kind":"symbol","title":"MapDataSource","type":"topic","fragments":[{"text":"class","kind":"keyword"},{"text":" ","kind":"text"},{"text":"MapDataSource","kind":"identifier"}]},"doc://MapsNativeSDK/documentation/MapsNativeSDK/SwiftUICore":{"url":"\/documentation\/mapsnativesdk\/swiftuicore","title":"SwiftUICore","abstract":[],"identifier":"doc:\/\/MapsNativeSDK\/documentation\/MapsNativeSDK\/SwiftUICore","type":"topic","kind":"symbol","role":"collection"},"doc://MapsNativeSDK/documentation/MapsNativeSDK/PaintColor":{"abstract":[],"kind":"symbol","title":"PaintColor","url":"\/documentation\/mapsnativesdk\/paintcolor","type":"topic","role":"symbol","navigatorTitle":[{"kind":"identifier","text":"PaintColor"}],"identifier":"doc:\/\/MapsNativeSDK\/documentation\/MapsNativeSDK\/PaintColor","fragments":[{"text":"enum","kind":"keyword"},{"text":" ","kind":"text"},{"text":"PaintColor","kind":"identifier"}]},"doc://MapsNativeSDK/documentation/MapsNativeSDK/MapAnimationEasing":{"type":"topic","fragments":[{"kind":"keyword","text":"enum"},{"kind":"text","text":" "},{"kind":"identifier","text":"MapAnimationEasing"}],"identifier":"doc:\/\/MapsNativeSDK\/documentation\/MapsNativeSDK\/MapAnimationEasing","role":"symbol","navigatorTitle":[{"kind":"identifier","text":"MapAnimationEasing"}],"url":"\/documentation\/mapsnativesdk\/mapanimationeasing","abstract":[],"kind":"symbol","title":"MapAnimationEasing"},"doc://MapsNativeSDK/documentation/MapsNativeSDK/CurrentLocationColors":{"role":"symbol","identifier":"doc:\/\/MapsNativeSDK\/documentation\/MapsNativeSDK\/CurrentLocationColors","title":"CurrentLocationColors","fragments":[{"kind":"keyword","text":"struct"},{"kind":"text","text":" "},{"kind":"identifier","text":"CurrentLocationColors"}],"url":"\/documentation\/mapsnativesdk\/currentlocationcolors","type":"topic","navigatorTitle":[{"kind":"identifier","text":"CurrentLocationColors"}],"kind":"symbol","abstract":[]},"doc://MapsNativeSDK/documentation/MapsNativeSDK/CoreGraphics":{"kind":"symbol","url":"\/documentation\/mapsnativesdk\/coregraphics","role":"collection","abstract":[],"identifier":"doc:\/\/MapsNativeSDK\/documentation\/MapsNativeSDK\/CoreGraphics","type":"topic","title":"CoreGraphics"},"doc://MapsNativeSDK/documentation/MapsNativeSDK/UserPointer":{"type":"topic","identifier":"doc:\/\/MapsNativeSDK\/documentation\/MapsNativeSDK\/UserPointer","url":"\/documentation\/mapsnativesdk\/userpointer","kind":"article","title":"Индикатор пользователя","role":"article","abstract":[{"type":"text","text":"Размещайте на карте маркер пользователя для указания его текущего местоположения и направления."}]},"doc://MapsNativeSDK/documentation/MapsNativeSDK/MapBaseNode":{"title":"MapBaseNode","kind":"symbol","abstract":[],"type":"topic","identifier":"doc:\/\/MapsNativeSDK\/documentation\/MapsNativeSDK\/MapBaseNode","navigatorTitle":[{"text":"MapBaseNode","kind":"identifier"}],"role":"symbol","url":"\/documentation\/mapsnativesdk\/mapbasenode","fragments":[{"text":"protocol","kind":"keyword"},{"text":" ","kind":"text"},{"text":"MapBaseNode","kind":"identifier"}]},"doc://MapsNativeSDK/documentation/MapsNativeSDK/MapNodeActionAnimationEasing":{"fragments":[{"text":"enum","kind":"keyword"},{"text":" ","kind":"text"},{"text":"MapNodeActionAnimationEasing","kind":"identifier"}],"url":"\/documentation\/mapsnativesdk\/mapnodeactionanimationeasing","title":"MapNodeActionAnimationEasing","abstract":[],"kind":"symbol","identifier":"doc:\/\/MapsNativeSDK\/documentation\/MapsNativeSDK\/MapNodeActionAnimationEasing","navigatorTitle":[{"text":"MapNodeActionAnimationEasing","kind":"identifier"}],"type":"topic","role":"symbol"},"doc://MapsNativeSDK/documentation/MapsNativeSDK/Coordinates":{"abstract":[],"url":"\/documentation\/mapsnativesdk\/coordinates","navigatorTitle":[{"kind":"identifier","text":"Coordinates"}],"type":"topic","fragments":[{"kind":"keyword","text":"struct"},{"kind":"text","text":" "},{"kind":"identifier","text":"Coordinates"}],"identifier":"doc:\/\/MapsNativeSDK\/documentation\/MapsNativeSDK\/Coordinates","kind":"symbol","role":"symbol","title":"Coordinates"},"doc://MapsNativeSDK/documentation/MapsNativeSDK/Foundation":{"url":"\/documentation\/mapsnativesdk\/foundation","kind":"symbol","title":"Foundation","identifier":"doc:\/\/MapsNativeSDK\/documentation\/MapsNativeSDK\/Foundation","role":"collection","abstract":[],"type":"topic"},"doc://MapsNativeSDK/documentation/MapsNativeSDK/FollowingMode":{"url":"\/documentation\/mapsnativesdk\/followingmode","title":"Режимы следования","kind":"article","abstract":[{"text":"Используйте режимы следования для определения логики привязки камеры к индикатору пользователя.","type":"text"}],"role":"article","identifier":"doc:\/\/MapsNativeSDK\/documentation\/MapsNativeSDK\/FollowingMode","type":"topic"},"doc://MapsNativeSDK/documentation/MapsNativeSDK/Angle":{"kind":"symbol","url":"\/documentation\/mapsnativesdk\/angle","type":"topic","abstract":[],"role":"symbol","title":"Angle","navigatorTitle":[{"text":"Angle","kind":"identifier"}],"identifier":"doc:\/\/MapsNativeSDK\/documentation\/MapsNativeSDK\/Angle","fragments":[{"text":"struct","kind":"keyword"},{"text":" ","kind":"text"},{"text":"Angle","kind":"identifier"}]},"doc://MapsNativeSDK/documentation/MapsNativeSDK/MapError":{"type":"topic","abstract":[],"title":"MapError","kind":"symbol","role":"symbol","fragments":[{"text":"enum","kind":"keyword"},{"text":" ","kind":"text"},{"text":"MapError","kind":"identifier"}],"identifier":"doc:\/\/MapsNativeSDK\/documentation\/MapsNativeSDK\/MapError","url":"\/documentation\/mapsnativesdk\/maperror","navigatorTitle":[{"text":"MapError","kind":"identifier"}]}}}